ipmt/__init__.py
ipmt/cli.py
ipmt/db.py
ipmt/error.py
ipmt/migration.py
ipmt/misc.py
ipmt/permissions.py
ipmt-2.3.dist-info/LICENSE
ipmt-2.3.dist-info/METADATA
ipmt-2.3.dist-info/WHEEL
ipmt-2.3.dist-info/entry_points.txt
ipmt-2.3.dist-info/RECORD
