Metadata-Version: 2.1
Name: ipmt
Version: 2.3
Summary: Schema migration tools for PostgreSQL
Home-page: https://github.com/inplat/ipmt
License: Apache-2.0
Keywords: ipmt
Author: InPlat
Author-email: dev@inplat.ru
Requires-Python: >=3.7,<4.0
Classifier: Development Status :: 2 - Pre-Alpha
Classifier: Intended Audience :: Developers
Classifier: License :: OSI Approved :: Apache Software License
Classifier: Natural Language :: Russian
Classifier: Programming Language :: Python :: 3
Classifier: Programming Language :: Python :: 3.7
Classifier: Programming Language :: Python :: 3.8
Classifier: Programming Language :: Python :: 3.9
Classifier: Programming Language :: Python :: 3.10
Classifier: Programming Language :: Python :: 3.11
Requires-Dist: Jinja2 (>=3.0.1,<4.0.0)
Requires-Dist: Mako (>=1.1.4,<2.0.0)
Requires-Dist: PyYAML (>=6.0.1,<7.0.0)
Requires-Dist: docker (>=6.1.3,<7.0.0)
Requires-Dist: psycopg2 (>=2.9.1,<3.0.0)
